mysite/__init__.py
mysite/asgi.py
mysite/settings.py
mysite/urls.py
mysite/wsgi.py
polls/__init__.py
polls/admin.py
polls/apps.py
polls/models.py
polls/tests.py
polls/urls.py
polls/views.py
polls/static/polls/style.css
polls/templates/polls/detail.html
polls/templates/polls/index.html
polls/templates/polls/results.html
django_polls_rednafi-0.1.4.dist-info/LICENSE
django_polls_rednafi-0.1.4.dist-info/METADATA
django_polls_rednafi-0.1.4.dist-info/WHEEL
django_polls_rednafi-0.1.4.dist-info/top_level.txt
django_polls_rednafi-0.1.4.dist-info/RECORD
