Metadata-Version: 2.1
Name: django-polls-rednafi
Version: 0.1.4
Summary: This is the canonical `polls` app from the Django tutorial.
Home-page: https://github.com/rednafi/django-polls
Author: Redowan Delowar
Author-email: redowan.nafi@gmail.com
License: MIT  # Example license
Platform: UNKNOWN
Classifier: Environment :: Web Environment
Classifier: Framework :: Django
Classifier: Intended Audience :: Developers
Classifier: License :: OSI Approved :: BSD License
Classifier: Operating System :: OS Independent
Classifier: Programming Language :: Python
Classifier: Programming Language :: Python :: 3
Classifier: Programming Language :: Python :: 3 :: Only
Classifier: Programming Language :: Python :: 3.8
Classifier: Programming Language :: Python :: 3.9
Classifier: Programming Language :: Python :: 3.10
Classifier: Topic :: Internet :: WWW/HTTP
Classifier: Topic :: Internet :: WWW/HTTP :: Dynamic Content
Requires-Python: >=3.8
License-File: LICENSE
Requires-Dist: Django (>=3.2)
Requires-Dist: tblib (>=1.7.0)
Provides-Extra: dev_deps
Requires-Dist: black ; extra == 'dev_deps'
Requires-Dist: flake8 ; extra == 'dev_deps'
Requires-Dist: isort ; extra == 'dev_deps'
Requires-Dist: twine ; extra == 'dev_deps'
Requires-Dist: build ; extra == 'dev_deps'
